{
    "hiring_companies": [
        {
            "blocks": null,
            "body": null,
            "cookies": null,
            "credentials": {
                "login": null,
                "password": null
            },
            "default_params": null,
            "fields": null,
            "headers": null,
            "integration_id": 10907,
            "integration_provider_id": 67,
            "is_python": true,
            "name": "Answering Service Care",
            "spider_name": "pay_com_career_page",
            "start_url": "https://www.paycomonline.net/v4/ats/web.php/jobs?clientkey=8839194A20ABF96F683B08D5273AC086",
            "status": 1,
            "url_params": []
        }
    ],
    "name": "Answering Service Care"
}