{
    "hiring_companies": [
        {
            "blocks": null,
            "body": null,
            "cookies": null,
            "credentials": {
                "login": null,
                "password": null
            },
            "default_params": null,
            "fields": null,
            "headers": null,
            "integration_id": 14196,
            "integration_provider_id": 120,
            "is_python": true,
            "name": "Artemis Real Estate Partners",
            "spider_name": "job_score_career_page",
            "start_url": "https://careers.jobscore.com/careers/artemisrealestatepartners",
            "status": 1,
            "url_params": []
        }
    ],
    "name": "Artemis Real Estate Partners"
}