{
    "hiring_companies": [
        {
            "blocks": null,
            "body": null,
            "cookies": null,
            "credentials": {
                "login": null,
                "password": null
            },
            "default_params": null,
            "fields": null,
            "headers": null,
            "integration_id": 30237,
            "integration_provider_id": 210,
            "is_python": true,
            "name": "Boerne, Texas",
            "spider_name": "government_jobs",
            "start_url": "https://www.governmentjobs.com/careers/boerne-tx",
            "status": 1,
            "url_params": []
        }
    ],
    "name": "Boerne, Texas"
}