{
    "hiring_companies": [
        {
            "blocks": null,
            "body": null,
            "cookies": null,
            "credentials": {
                "login": null,
                "password": null
            },
            "default_params": null,
            "fields": null,
            "headers": null,
            "integration_id": 6450,
            "integration_provider_id": 108,
            "is_python": true,
            "name": "Canon Medical Systems",
            "spider_name": "adp_workforce_career_page",
            "start_url": "https://workforcenow.adp.com/mascsr/default/careercenter/public/events/staffing/v1/job-requisitions?cid=941f165b-9d12-4257-bdfb-e4241f494540&lang=en_US&locale=en_US&top=20",
            "status": 1,
            "url_params": []
        }
    ],
    "name": "Canon Medical Systems"
}