{
    "hiring_companies": [
        {
            "blocks": null,
            "body": null,
            "cookies": null,
            "credentials": {
                "login": null,
                "password": null
            },
            "default_params": null,
            "fields": null,
            "headers": null,
            "integration_id": 11420,
            "integration_provider_id": 67,
            "is_python": true,
            "name": "Chesapeake Conservancy",
            "spider_name": "pay_com_career_page",
            "start_url": "https://www.paycomonline.net/v4/ats/web.php/jobs?clientkey=14B329E3D0A2E479F3FE06280008FB70",
            "status": 1,
            "url_params": []
        }
    ],
    "name": "Chesapeake Conservancy"
}