{
    "hiring_companies": [
        {
            "blocks": null,
            "body": null,
            "cookies": null,
            "credentials": {
                "login": null,
                "password": null
            },
            "default_params": null,
            "fields": null,
            "headers": null,
            "integration_id": 4217,
            "integration_provider_id": 30,
            "is_python": true,
            "name": "Cognex",
            "spider_name": "workday",
            "start_url": "https://cognex.wd1.myworkdayjobs.com/es/External_Career_Site",
            "status": 1,
            "url_params": []
        }
    ],
    "name": "Cognex"
}