{
    "hiring_companies": [
        {
            "blocks": null,
            "body": null,
            "cookies": null,
            "credentials": {
                "login": null,
                "password": null
            },
            "default_params": null,
            "fields": null,
            "headers": null,
            "integration_id": 27471,
            "integration_provider_id": 44,
            "is_python": true,
            "name": "Credit One Bank",
            "spider_name": "dayforce_career_page",
            "start_url": "https://us60.dayforcehcm.com/CandidatePortal/en-US/creditonebank",
            "status": 1,
            "url_params": []
        }
    ],
    "name": "Credit One Bank"
}