{
    "hiring_companies": [
        {
            "blocks": null,
            "body": null,
            "cookies": null,
            "credentials": {
                "login": null,
                "password": null
            },
            "default_params": null,
            "fields": null,
            "headers": null,
            "integration_id": 13491,
            "integration_provider_id": 130,
            "is_python": true,
            "name": "Cresthill Academy",
            "spider_name": "bamboo_hr",
            "start_url": "https://cresthillacademy.bamboohr.com/jobs/",
            "status": 1,
            "url_params": []
        }
    ],
    "name": "Cresthill Academy"
}