{
    "hiring_companies": [
        {
            "blocks": null,
            "body": null,
            "cookies": null,
            "credentials": {
                "login": null,
                "password": null
            },
            "default_params": null,
            "fields": null,
            "headers": null,
            "integration_id": 6575,
            "integration_provider_id": 108,
            "is_python": true,
            "name": "Draper Aden Associates",
            "spider_name": "adp_workforce_career_page",
            "start_url": "https://workforcenow.adp.com/mascsr/default/careercenter/public/events/staffing/v1/job-requisitions?cid=32da9d8b-3d46-4ccd-89ae-1c4398ec9936&lang=en_US&locale=en_US&top=20",
            "status": 1,
            "url_params": []
        }
    ],
    "name": "Draper Aden Associates"
}