{
    "hiring_companies": [
        {
            "blocks": null,
            "body": null,
            "cookies": null,
            "credentials": {
                "login": null,
                "password": null
            },
            "default_params": null,
            "fields": null,
            "headers": null,
            "integration_id": 10146,
            "integration_provider_id": 34,
            "is_python": true,
            "name": "Alaka`ina Foundation Family of Companies",
            "spider_name": "taleo_career_page",
            "start_url": "https://phg.tbe.taleo.net/phg04/ats/careers/v2/searchResults?org=AKIMEKATECH&cws=43",
            "status": 1,
            "url_params": []
        }
    ],
    "name": "familyofcompanies"
}