{
    "hiring_companies": [
        {
            "blocks": null,
            "body": null,
            "cookies": null,
            "credentials": {
                "login": null,
                "password": null
            },
            "default_params": null,
            "fields": null,
            "headers": null,
            "integration_id": 6628,
            "integration_provider_id": 108,
            "is_python": true,
            "name": "First Baptist Church of Glenarden",
            "spider_name": "adp_workforce_career_page",
            "start_url": "https://workforcenow.adp.com/mascsr/default/careercenter/public/events/staffing/v1/job-requisitions?cid=0a7f894f-a98a-4f83-b742-7822cd94837a&lang=en_US&locale=en_US&top=20",
            "status": 1,
            "url_params": []
        }
    ],
    "name": "First Baptist Church of Glenarden"
}