{
    "hiring_companies": [
        {
            "blocks": null,
            "body": null,
            "cookies": null,
            "credentials": {
                "login": null,
                "password": null
            },
            "default_params": null,
            "fields": null,
            "headers": null,
            "integration_id": 15697,
            "integration_provider_id": 33,
            "is_python": true,
            "name": "Goodwill of Western Missouri & Eastern Kansas",
            "spider_name": "icims_career_page",
            "start_url": "https://careers-mokangoodwill.icims.com/sitemap.xml",
            "status": 1,
            "url_params": []
        }
    ],
    "name": "Goodwill of Western Missouri & Eastern Kansas"
}