{
    "hiring_companies": [
        {
            "blocks": null,
            "body": null,
            "cookies": null,
            "credentials": {
                "login": null,
                "password": null
            },
            "default_params": null,
            "fields": null,
            "headers": null,
            "integration_id": 19376,
            "integration_provider_id": 69,
            "is_python": true,
            "name": "Gray Television",
            "spider_name": "ultipro_recruiting_career_page",
            "start_url": "https://recruiting.ultipro.com/GRA1017GRYT/JobBoard/ae441110-89bd-444d-8ad2-b76c7b9db7a9",
            "status": 1,
            "url_params": []
        }
    ],
    "name": "Gray Television"
}