{
    "hiring_companies": [
        {
            "blocks": null,
            "body": null,
            "cookies": null,
            "credentials": {
                "login": null,
                "password": null
            },
            "default_params": null,
            "fields": null,
            "headers": null,
            "integration_id": 10440,
            "integration_provider_id": 69,
            "is_python": true,
            "name": "H&L Partners",
            "spider_name": "ultipro_recruiting_career_page",
            "start_url": "https://recruiting2.ultipro.com/HLP1000HLPS/JobBoard/52dfce5b-63a1-42bc-bc85-701b3ce629b5",
            "status": 1,
            "url_params": []
        }
    ],
    "name": "H&L Partners"
}