{
    "hiring_companies": [
        {
            "blocks": null,
            "body": null,
            "cookies": null,
            "credentials": {
                "login": null,
                "password": null
            },
            "default_params": null,
            "fields": null,
            "headers": null,
            "integration_id": 6042,
            "integration_provider_id": 47,
            "is_python": true,
            "name": "HipoGes Iberia",
            "spider_name": "cornerstone_career_page",
            "start_url": "https://hipoges.csod.com/ux/ats/careersite/6/home?c=hipoges",
            "status": 1,
            "url_params": []
        }
    ],
    "name": "HipoGes Iberia"
}