{
    "hiring_companies": [
        {
            "blocks": null,
            "body": null,
            "cookies": null,
            "credentials": {
                "login": null,
                "password": null
            },
            "default_params": null,
            "fields": null,
            "headers": null,
            "integration_id": 14382,
            "integration_provider_id": 126,
            "is_python": true,
            "name": "Homeway Homes",
            "spider_name": "zoho_public_career_page",
            "start_url": "https://homewayhomes.zohorecruit.com/recruit/Portal.na?iframe=true&digest=3hFBA4Da3AkqLKjJ34kXhStoJi6k6l26%40XJqAOevt1w-",
            "status": 1,
            "url_params": []
        }
    ],
    "name": "Homeway Homes"
}