{
    "hiring_companies": [
        {
            "blocks": null,
            "body": null,
            "cookies": null,
            "credentials": {
                "login": null,
                "password": null
            },
            "default_params": null,
            "fields": null,
            "headers": null,
            "integration_id": 10512,
            "integration_provider_id": 69,
            "is_python": true,
            "name": "Minnesota Gastroenterology",
            "spider_name": "ultipro_recruiting_career_page",
            "start_url": "https://recruiting2.ultipro.com/MIN1002MNGAS/JobBoard/9036af08-f14f-4f3e-9c19-b80777d7f677",
            "status": 1,
            "url_params": []
        }
    ],
    "name": "Minnesota Gastroenterology"
}