{
    "hiring_companies": [
        {
            "blocks": null,
            "body": null,
            "cookies": null,
            "credentials": {
                "login": null,
                "password": null
            },
            "default_params": null,
            "fields": null,
            "headers": null,
            "integration_id": 15491,
            "integration_provider_id": 69,
            "is_python": true,
            "name": "Neptune Technology Group",
            "spider_name": "ultipro_recruiting_career_page",
            "start_url": "https://recruiting.ultipro.com/ROP1001ROPER/JobBoard/9e6d300d-93f8-4db8-b9df-53a127fb74af",
            "status": 1,
            "url_params": []
        }
    ],
    "name": "Neptune Technology Group"
}