{
    "hiring_companies": [
        {
            "blocks": null,
            "body": null,
            "cookies": null,
            "credentials": {
                "login": null,
                "password": null
            },
            "default_params": null,
            "fields": null,
            "headers": null,
            "integration_id": 11191,
            "integration_provider_id": 67,
            "is_python": true,
            "name": "OrganicKrush",
            "spider_name": "pay_com_career_page",
            "start_url": "https://www.paycomonline.net/v4/ats/web.php/jobs?clientkey=D6C1848C2C272E9A1195E99292C6B4CB",
            "status": 1,
            "url_params": []
        }
    ],
    "name": "OrganicKrush"
}