{
    "hiring_companies": [
        {
            "blocks": null,
            "body": null,
            "cookies": null,
            "credentials": {
                "login": null,
                "password": null
            },
            "default_params": null,
            "fields": null,
            "headers": null,
            "integration_id": 11194,
            "integration_provider_id": 67,
            "is_python": true,
            "name": "PCS Structural Solutions",
            "spider_name": "pay_com_career_page",
            "start_url": "https://www.paycomonline.net/v4/ats/web.php/jobs?clientkey=772C3279D75E0FFAB33570D71B96316D",
            "status": 1,
            "url_params": []
        }
    ],
    "name": "PCS Structural Solutions"
}