{
    "hiring_companies": [
        {
            "blocks": null,
            "body": null,
            "cookies": null,
            "credentials": {
                "login": null,
                "password": null
            },
            "default_params": null,
            "fields": null,
            "headers": null,
            "integration_id": 14393,
            "integration_provider_id": 126,
            "is_python": true,
            "name": "Performance Excellence Partners",
            "spider_name": "zoho_public_career_page",
            "start_url": "https://performexcel.zohorecruit.com/recruit/Portal.na?iframe=true&digest=vYEnbI1YdaMDoy.nnSwCanGAUnkE7bVo.a85bxdBEmQ-",
            "status": 1,
            "url_params": []
        }
    ],
    "name": "Performance Excellence Partners"
}