{
    "hiring_companies": [
        {
            "blocks": null,
            "body": null,
            "cookies": null,
            "credentials": {
                "login": null,
                "password": null
            },
            "default_params": null,
            "fields": null,
            "headers": null,
            "integration_id": 26051,
            "integration_provider_id": 185,
            "is_python": true,
            "name": "Pine Valley Rehab",
            "spider_name": "apploi",
            "start_url": "https://jobs.apploi.com/profile/pine-valley",
            "status": 1,
            "url_params": []
        }
    ],
    "name": "Pine Valley Rehab"
}