{
    "hiring_companies": [
        {
            "blocks": null,
            "body": null,
            "cookies": null,
            "credentials": {
                "login": null,
                "password": null
            },
            "default_params": null,
            "fields": null,
            "headers": null,
            "integration_id": 9299,
            "integration_provider_id": 111,
            "is_python": true,
            "name": "PREMIER System Integrators",
            "spider_name": "paylocity",
            "start_url": "https://recruiting.paylocity.com/Recruiting/Jobs/All/f39eb1d4-e4c7-4264-8cc8-2e93d25ffb93",
            "status": 1,
            "url_params": []
        }
    ],
    "name": "PREMIER System Integrators"
}