{
    "hiring_companies": [
        {
            "blocks": null,
            "body": null,
            "cookies": null,
            "credentials": {
                "login": null,
                "password": null
            },
            "default_params": null,
            "fields": null,
            "headers": null,
            "integration_id": 23592,
            "integration_provider_id": 47,
            "is_python": true,
            "name": "Rochester Electronics",
            "spider_name": "cornerstone_career_page",
            "start_url": "https://workatrochester.csod.com/ux/ats/careersite/1/home?c=workatrochester",
            "status": 1,
            "url_params": []
        }
    ],
    "name": "Rochester Electronics"
}