{
    "hiring_companies": [
        {
            "blocks": null,
            "body": null,
            "cookies": null,
            "credentials": {
                "login": null,
                "password": null
            },
            "default_params": null,
            "fields": null,
            "headers": null,
            "integration_id": 25954,
            "integration_provider_id": 183,
            "is_python": true,
            "name": "Third & Hollywood",
            "spider_name": "harri",
            "start_url": "https://harri.com/Third---Hollywood-1",
            "status": 1,
            "url_params": []
        }
    ],
    "name": "Third & Hollywood"
}